aiosfstream/__init__.py
aiosfstream/_metadata.py
aiosfstream/auth.py
aiosfstream/client.py
aiosfstream/exceptions.py
aiosfstream/py.typed
aiosfstream/replay.py
aiosfstream-0.5.0.dist-info/LICENSE.txt
aiosfstream-0.5.0.dist-info/METADATA
aiosfstream-0.5.0.dist-info/WHEEL
aiosfstream-0.5.0.dist-info/top_level.txt
aiosfstream-0.5.0.dist-info/RECORD
