Metadata-Version: 2.1
Name: aiosfstream
Version: 0.5.0
Summary: Salesforce Streaming API client for asyncio
Home-page: https://github.com/robertmrk/aiosfstream
Author: Róbert Márki
Author-email: gsmiko@gmail.com
License: MIT
Project-URL: CI, https://travis-ci.org/robertmrk/aiosfstream
Project-URL: Coverage, https://coveralls.io/github/robertmrk/aiosfstream
Project-URL: Docs, http://aiosfstream.readthedocs.io/
Keywords: salesforce asyncio aiohttp comet cometd bayeux push streaming
Platform: UNKNOWN
Classifier: Programming Language :: Python
Classifier: Programming Language :: Python :: 3
Classifier: Programming Language :: Python :: 3.6
Classifier: Programming Language :: Python :: Implementation :: CPython
Classifier: Framework :: AsyncIO
Classifier: License :: OSI Approved :: MIT License
Requires-Python: >=3.6.0
Requires-Dist: aiocometd (<0.5.0,>=0.4.1)
Requires-Dist: aiohttp (<4.0,>=3.1)
Provides-Extra: dev
Requires-Dist: asynctest (<1.0.0,>=0.12.0) ; extra == 'dev'
Requires-Dist: coverage (<5.0,>=4.5) ; extra == 'dev'
Requires-Dist: flake8 ; extra == 'dev'
Requires-Dist: pylint ; extra == 'dev'
Requires-Dist: mypy ; extra == 'dev'
Requires-Dist: Sphinx (<2.0,>=1.7) ; extra == 'dev'
Requires-Dist: sphinxcontrib-asyncio (>=0.2.0) ; extra == 'dev'
Requires-Dist: sphinx-autodoc-typehints ; extra == 'dev'
Provides-Extra: docs
Requires-Dist: Sphinx (<2.0,>=1.7) ; extra == 'docs'
Requires-Dist: sphinxcontrib-asyncio (>=0.2.0) ; extra == 'docs'
Requires-Dist: sphinx-autodoc-typehints ; extra == 'docs'
Provides-Extra: tests
Requires-Dist: asynctest (<1.0.0,>=0.12.0) ; extra == 'tests'
Requires-Dist: coverage (<5.0,>=4.5) ; extra == 'tests'
Requires-Dist: flake8 ; extra == 'tests'
Requires-Dist: pylint ; extra == 'tests'
Requires-Dist: mypy ; extra == 'tests'
